{"statistical_data": {"friends_num": 6, "active_num": 5, "error_num": 1, "article_num": 10, "last_updated_time": "2024-04-02 09:45:02"}, "article_data": [{"floor": 1, "title": "\u4e66\u7c4d\u63a8\u8350\u2014\u2014\u300a\u81ea\u5b66\u662f\u95e8\u624b\u827a\u300b", "created": "2024-03-23", "updated": "2024-03-23", "link": "http://achuan-2.top/post/book-recommendation-self-study-is-the-door-craft-zja4yb.html", "author": "Achuan-2", "avatar": "https://fastly.jsdelivr.net/gh/Achuan-2/Picbed@pic/assets/1666805474234Achuan.jpg"}, {"floor": 2, "title": "\u514d\u8d39\u5546\u7528\u5b57\u4f53\uff1a\u4e61\u7acb\u65b9\u9ed1\u4f53", "created": "2024-03-20", "updated": "2024-03-20", "link": "https://blog.zhheo.com/p/e07d9639.html", "author": "\u5f20\u6d2aHeo", "avatar": "https://bu.dusays.com/2022/12/28/63ac2812183aa.png"}, {"floor": 3, "title": "\u8baf\u98de\u667a\u6587\u4e0a\u624b\uff1a\u5927\u7eb2\u4e00\u952e\u53d8PPT\uff0c\u592a\u723d\u4e86", "created": "2024-03-19", "updated": "2024-03-19", "link": "https://blog.zhheo.com/p/f71022b8.html", "author": "\u5f20\u6d2aHeo", "avatar": "https://bu.dusays.com/2022/12/28/63ac2812183aa.png"}, {"floor": 4, "title": "\u6606\u4ed1\u5de2\u300c\u75af\u72c2\u661f\u671f\u516d\u300d\uff0c\u6ca1\u6709\u4eba\u662f\u4e00\u5ea7\u5b64\u5c9b\uff5e", "created": "2024-03-18", "updated": "2024-03-18", "link": "https://blog.sunguoqi.com/posts/kunlunchao/", "author": "\u5c0f\u5b59\u540c\u5b66", "avatar": "https://blog.sunguoqi.com/images/avatar.jpg"}, {"floor": 5, "title": "\u5982\u4f55\u63d0\u5347iPhone\u7684\u9501\u5c4f\u901f\u5ea6", "created": "2024-03-12", "updated": "2024-03-12", "link": "https://blog.zhheo.com/p/41b1e1ce.html", "author": "\u5f20\u6d2aHeo", "avatar": "https://bu.dusays.com/2022/12/28/63ac2812183aa.png"}, {"floor": 6, "title": "\u4f60\u597d\uff0c\u5317\u4eac\uff01\u4f60\u597d\uff0c\u539f\u5219\u79d1\u6280\uff01\u4e00\u5207\u90fd\u662f\u6700\u597d\u7684\u5b89\u6392\uff01", "created": "2024-03-10", "updated": "2024-03-10", "link": "https://blog.sunguoqi.com/posts/yuanze/", "author": "\u5c0f\u5b59\u540c\u5b66", "avatar": "https://blog.sunguoqi.com/images/avatar.jpg"}, {"floor": 7, "title": "\u7528Gemini\uff0c\u5b9e\u73b0AI\u6458\u8981", "created": "2024-03-09", "updated": "2024-03-09", "link": "https://blog.hzchu.top/2024/%E7%94%A8Gemini%E5%AE%9E%E7%8E%B0AI%E6%91%98%E8%A6%81/", "author": "Thun888's Blog", "avatar": "https://blog.hzchu.top/img/avatar.webp"}, {"floor": 8, "title": "\u8bb0\u4e00\u6b21\u6392\u67e5js\u6587\u4ef6\u540e\u95e8", "created": "2024-03-08", "updated": "2024-03-08", "link": "https://blog.hzchu.top/2024/%E8%AE%B0%E4%B8%80%E6%AC%A1%E6%8E%92%E6%9F%A5js%E6%96%87%E4%BB%B6%E5%90%8E%E9%97%A8/", "author": "Thun888's Blog", "avatar": "https://blog.hzchu.top/img/avatar.webp"}, {"floor": 9, "title": "AutoCode\u4e0a\u624b\uff1a\u8ba9Mac\u652f\u6301\u81ea\u52a8\u586b\u5145\u6765\u81ea\u624b\u673a\u7684\u9a8c\u8bc1\u7801", "created": "2024-03-07", "updated": "2024-03-07", "link": "https://blog.zhheo.com/p/6bbc14a1.html", "author": "\u5f20\u6d2aHeo", "avatar": "https://bu.dusays.com/2022/12/28/63ac2812183aa.png"}, {"floor": 10, "title": "\u7528Python\u6279\u91cf\u7ed9\u626b\u63cfpdf\u6dfb\u52a0\u4e66\u7b7e", "created": "2024-03-06", "updated": "2024-03-06", "link": "http://achuan-2.top/post/scan-the-pdf-batch-with-python-batch-to-add-bookmarks-zn2z7s.html", "author": "Achuan-2", "avatar": "https://fastly.jsdelivr.net/gh/Achuan-2/Picbed@pic/assets/1666805474234Achuan.jpg"}]}